aws_recommendation_a7/__init__.py
aws_recommendation_a7/cloudwatch.py
aws_recommendation_a7/cost_estimations.py
aws_recommendation_a7/dynamodb.py
aws_recommendation_a7/ebs.py
aws_recommendation_a7/ec2.py
aws_recommendation_a7/elb.py
aws_recommendation_a7/kms.py
aws_recommendation_a7/rds.py
aws_recommendation_a7/recommendation.py
aws_recommendation_a7/redshift.py
aws_recommendation_a7/s3.py
aws_recommendation_a7/truted_advisor.py
aws_recommendation_a7/utils.py
aws_recommendation_a7-0.0.19.dist-info/LICENCE
aws_recommendation_a7-0.0.19.dist-info/METADATA
aws_recommendation_a7-0.0.19.dist-info/WHEEL
aws_recommendation_a7-0.0.19.dist-info/top_level.txt
aws_recommendation_a7-0.0.19.dist-info/RECORD
